{
    "title": "Perils of Perception survey 2016",
    "Country": "Mexico",
    "questions": [
        {
            "id": 20,
            "text": "现在展望2020年，你认为在墨西哥每100个人有多少人是穆斯林？",
            "answer": "0",
            "options": [
                0,
                100
            ],
            "meta": {
                "qid": "q4",
                "perceived": "11"
            },
            "responses": {
                "0": 30,
                "1": 20,
                "2": 16,
                "3": 9,
                "4": 1,
                "5": 6,
                "6": 1,
                "10": 1,
                "11": 1,
                "15": 1,
                "25": 1,
                "75": 1
            }
        },
        {
            "id": 27,
            "text": "在墨西哥的一项调查中，你觉得有多少百分比的人认为同性恋在道德上是不可接受的？",
            "answer": "40",
            "options": [
                0,
                100
            ],
            "meta": {
                "qid": "q14",
                "perceived": "59"
            },
            "responses": {
                "1": 1,
                "10": 1,
                "20": 1,
                "30": 3,
                "31": 2,
                "33": 1,
                "35": 2,
                "37": 1,
                "40": 6,
                "44": 2,
                "46": 3,
                "48": 1,
                "49": 1,
                "50": 5,
                "51": 1,
                "53": 2,
                "54": 1,
                "55": 1,
                "57": 2,
                "59": 1,
                "60": 6,
                "61": 2,
                "62": 1,
                "63": 2,
                "64": 1,
                "65": 1,
                "66": 2,
                "68": 4,
                "69": 2,
                "70": 8,
                "71": 1,
                "72": 1,
                "74": 1,
                "75": 3,
                "76": 1,
                "77": 2,
                "78": 1,
                "80": 4,
                "81": 1,
                "86": 2,
                "90": 1
            }
        },
        {
            "id": 21,
            "text": "你认为墨西哥有多少百分比的国内生产总值（GDP）花在医疗保健支出上？",
            "answer": "6",
            "options": [
                0,
                100
            ],
            "meta": {
                "qid": "q5",
                "perceived": "19"
            },
            "responses": {
                "1": 1,
                "2": 2,
                "3": 3,
                "4": 4,
                "5": 5,
                "6": 3,
                "7": 4,
                "8": 3,
                "9": 3,
                "10": 9,
                "11": 5,
                "12": 5,
                "14": 1,
                "15": 10,
                "16": 5,
                "17": 1,
                "18": 3,
                "20": 8,
                "21": 1,
                "22": 1,
                "23": 1,
                "25": 2,
                "26": 1,
                "30": 2,
                "35": 2,
                "40": 2
            }
        },
        {
            "id": 19,
            "text": "你认为在墨西哥每100个人当中有多少人是穆斯林？",
            "answer": "0",
            "options": [
                0,
                100
            ],
            "meta": {
                "qid": "q3",
                "perceived": "8"
            },
            "responses": {
                "0": 17,
                "1": 23,
                "2": 11,
                "3": 14,
                "4": 6,
                "5": 6,
                "6": 3,
                "8": 1,
                "9": 1,
                "10": 3,
                "15": 2,
                "29": 1,
                "70": 1
            }
        },
        {
            "id": 24,
            "text": "在墨西哥的一项调查中，你觉得百分之多少的人表示，总体而言他们非常幸福或相对幸福？",
            "answer": "94",
            "options": [
                0,
                100
            ],
            "meta": {
                "qid": "q10",
                "perceived": "43"
            },
            "responses": {
                "7": 1,
                "9": 1,
                "18": 1,
                "20": 1,
                "22": 1,
                "30": 1,
                "34": 1,
                "35": 1,
                "40": 3,
                "45": 1,
                "49": 1,
                "50": 2,
                "51": 1,
                "52": 1,
                "53": 1,
                "55": 1,
                "60": 4,
                "61": 1,
                "62": 2,
                "63": 1,
                "65": 1,
                "66": 1,
                "69": 2,
                "70": 10,
                "71": 2,
                "72": 1,
                "73": 1,
                "74": 3,
                "75": 4,
                "76": 1,
                "77": 1,
                "78": 3,
                "79": 1,
                "80": 5,
                "82": 1,
                "83": 1,
                "84": 1,
                "85": 4,
                "87": 1,
                "88": 1,
                "90": 7,
                "91": 1,
                "92": 1,
                "94": 1,
                "95": 2,
                "97": 1
            }
        },
        {
            "id": 22,
            "text": "在墨西哥，每100个住宅中有多少是归住户所有的（拥有全部房产权或进行了房屋抵押）？",
            "answer": "76",
            "options": [
                0,
                100
            ],
            "meta": {
                "qid": "q6",
                "perceived": "45"
            },
            "responses": {
                "2": 1,
                "8": 2,
                "10": 2,
                "11": 1,
                "12": 1,
                "15": 5,
                "16": 1,
                "20": 5,
                "22": 1,
                "23": 1,
                "24": 2,
                "26": 2,
                "28": 2,
                "30": 5,
                "33": 2,
                "35": 3,
                "36": 1,
                "37": 1,
                "40": 8,
                "41": 2,
                "45": 3,
                "50": 3,
                "51": 1,
                "53": 1,
                "59": 1,
                "60": 7,
                "65": 3,
                "66": 2,
                "67": 1,
                "70": 6,
                "74": 1,
                "77": 1,
                "78": 1,
                "80": 3,
                "81": 1,
                "90": 3
            }
        },
        {
            "id": 23,
            "text": "你认为，墨西哥最不富裕的70%人们，其所拥有的家庭财富，占墨西哥全体家庭财富的百分比是多少？这边说的‘财富’，指是一个家庭所拥有的总价值减去该家庭欠下的所有债务（例如贷款和抵押）。",
            "answer": "15",
            "options": [
                0,
                100
            ],
            "meta": {
                "qid": "q7",
                "perceived": "31"
            },
            "responses": {
                "1": 1,
                "2": 2,
                "3": 3,
                "5": 5,
                "6": 4,
                "7": 1,
                "8": 1,
                "9": 3,
                "10": 10,
                "12": 2,
                "13": 1,
                "14": 2,
                "15": 8,
                "16": 1,
                "17": 1,
                "18": 2,
                "20": 15,
                "21": 1,
                "22": 1,
                "25": 1,
                "30": 8,
                "36": 2,
                "40": 2,
                "47": 1,
                "50": 1,
                "53": 1,
                "57": 1,
                "59": 1,
                "60": 1,
                "82": 1,
                "96": 1,
                "98": 1
            }
        },
        {
            "id": 26,
            "text": "在墨西哥的一项调查中，你觉得有多少百分比的人认为堕胎在道德上是不可接受的？",
            "answer": "63",
            "options": [
                0,
                100
            ],
            "meta": {
                "qid": "q12",
                "perceived": "61"
            },
            "responses": {
                "1": 1,
                "7": 1,
                "15": 2,
                "20": 3,
                "21": 1,
                "26": 1,
                "29": 3,
                "30": 3,
                "40": 3,
                "45": 1,
                "49": 1,
                "50": 6,
                "51": 1,
                "52": 1,
                "54": 1,
                "55": 1,
                "57": 1,
                "59": 2,
                "60": 8,
                "62": 2,
                "65": 2,
                "66": 2,
                "70": 5,
                "71": 1,
                "72": 2,
                "73": 2,
                "75": 5,
                "76": 1,
                "80": 7,
                "81": 1,
                "83": 1,
                "85": 4,
                "86": 1,
                "88": 2,
                "90": 3,
                "94": 1,
                "95": 1,
                "96": 1
            }
        },
        {
            "id": 28,
            "text": "在墨西哥的一项调查中，你觉得有多少百分比的人认为未婚成年人进行性行为在道德上是不可接受的？",
            "answer": "44",
            "options": [
                0,
                100
            ],
            "meta": {
                "qid": "q16",
                "perceived": "39"
            },
            "responses": {
                "5": 3,
                "10": 2,
                "12": 1,
                "13": 1,
                "14": 1,
                "15": 6,
                "17": 1,
                "18": 1,
                "19": 1,
                "20": 11,
                "24": 2,
                "27": 1,
                "28": 3,
                "29": 2,
                "30": 3,
                "32": 3,
                "33": 3,
                "34": 1,
                "35": 2,
                "38": 1,
                "40": 2,
                "41": 2,
                "42": 1,
                "43": 1,
                "44": 1,
                "49": 1,
                "50": 4,
                "52": 1,
                "53": 1,
                "57": 1,
                "58": 1,
                "60": 4,
                "62": 1,
                "68": 1,
                "69": 2,
                "70": 1,
                "71": 2,
                "73": 1,
                "75": 1,
                "77": 1,
                "80": 1,
                "81": 1,
                "90": 2,
                "93": 1
            }
        },
        {
            "id": 17,
            "text": "你认为墨西哥现在的人口是多少？这里的‘人口’指所有墨西哥全体居民，不考虑法律地位或公民身份。你的答案请以百万为单位。",
            "answer": "119.53",
            "options": [
                0,
                99999
            ],
            "meta": {
                "qid": "q1",
                "perceived": "120"
            },
            "responses": {
                "12": 1,
                "38": 1,
                "55": 1,
                "79": 1,
                "85": 1,
                "100": 1,
                "115": 1,
                "118": 1,
                "99999": 1
            }
        },
        {
            "id": 18,
            "text": "你认为联合国预计的2050年墨西哥人口是多少？你的答案请以百万为单位。",
            "answer": "163.75",
            "options": [
                0,
                99999
            ],
            "meta": {
                "qid": "q2",
                "perceived": "158"
            },
            "responses": {
                "13": 1,
                "44": 1,
                "70": 1,
                "96": 1,
                "99": 1,
                "140": 1,
                "150": 1,
                "200": 1,
                "99999": 1
            }
        }
    ]
}